cgroups_exporter/__init__.py
cgroups_exporter/__main__.py
cgroups_exporter/args.py
cgroups_exporter/metrics/__init__.py
cgroups_exporter/metrics/_metrics.py
cgroups_exporter/metrics/base.py
cgroups_exporter/metrics/blkio.py
cgroups_exporter/metrics/cpu.py
cgroups_exporter/metrics/cpuset.py
cgroups_exporter/metrics/meminfo.py
cgroups_exporter/metrics/memory.py
cgroups_exporter/metrics/pids.py
cgroups_exporter/metrics/unified.py
cgroups_exporter/services/__init__.py
cgroups_exporter/services/collector.py
cgroups_exporter/services/metrics.py
cgroups_exporter-0.8.8.dist-info/LICENSE
cgroups_exporter-0.8.8.dist-info/METADATA
cgroups_exporter-0.8.8.dist-info/WHEEL
cgroups_exporter-0.8.8.dist-info/entry_points.txt
cgroups_exporter-0.8.8.dist-info/RECORD
