Metadata-Version: 2.1
Name: cgroups-exporter
Version: 0.8.8
Summary: prometheus exporter for cgroups v1
Home-page: https://github.com/mosquito/cgroups-exporter
License: Apache Software License
Author: Dmitry Orlov
Author-email: me@mosquito.su
Requires-Python: >=3.8,<4.0
Classifier: Intended Audience :: Developers
Classifier: License :: OSI Approved :: Apache Software License
Classifier: License :: Other/Proprietary License
Classifier: Natural Language :: English
Classifier: Operating System :: MacOS
Classifier: Operating System :: Microsoft
Classifier: Operating System :: POSIX
Classifier: Programming Language :: Python
Classifier: Programming Language :: Python :: 3
Classifier: Programming Language :: Python :: 3.8
Classifier: Programming Language :: Python :: 3.9
Classifier: Programming Language :: Python :: 3.10
Classifier: Programming Language :: Python :: 3.11
Classifier: Programming Language :: Python :: 3.12
Classifier: Programming Language :: Python :: Implementation :: CPython
Classifier: Topic :: Software Development
Classifier: Topic :: Software Development :: Libraries
Requires-Dist: aiochannel (>=1.2.1,<2.0.0)
Requires-Dist: aiohttp (==3.9.0)
Requires-Dist: aiomisc (>=17.5,<18.0)
Requires-Dist: argclass (>=1.0,<2.0)
Project-URL: Source, https://github.com/mosquito/cgroups-exporter/
Project-URL: Say Thanks!, https://saythanks.io/to/mosquito
Project-URL: Tracker, https://github.com/mosquito/cgroups-exporter/issues
